migedit.py
migedit-0.3.4.dist-info/entry_points.txt
migedit-0.3.4.dist-info/LICENSE
migedit-0.3.4.dist-info/WHEEL
migedit-0.3.4.dist-info/METADATA
migedit-0.3.4.dist-info/RECORD
