Metadata-Version: 2.1
Name: migedit
Version: 0.3.4
Summary: MIG Editor. CLI/importable module to automatically delete and create MIG gpu/cpu instances.
Author-email: Ties Robroek <migedit@trobroek.com>
Requires-Python: >=3.10.0
Classifier: License :: OSI Approved :: MIT License
Project-URL: Home, https://github.com/Sipondo/migedit
